fastquotes/__init__.py
fastquotes/cli.py
fastquotes/const.py
fastquotes/stock_list.py
fastquotes/to_hans.py
fastquotes/trade_calendar.py
fastquotes/utils.py
fastquotes/async_quotes/__init__.py
fastquotes/async_quotes/async_quote.py
fastquotes/async_quotes/async_sina.py
fastquotes/async_quotes/async_tencent.py
fastquotes/coin/__init__.py
fastquotes/fund/__init__.py
fastquotes/fund/daily.py
fastquotes/fund/history.py
fastquotes/index/__init__.py
fastquotes/index/csi.py
fastquotes/quotes/__init__.py
fastquotes/quotes/quote.py
fastquotes/quotes/sina.py
fastquotes/quotes/tencent.py
fastquotes/static/trade_days.txt
fastquotes/stock/__init__.py
fastquotes/stock/exit_right.py
fastquotes-0.2.0.dist-info/LICENSE
fastquotes-0.2.0.dist-info/METADATA
fastquotes-0.2.0.dist-info/WHEEL
fastquotes-0.2.0.dist-info/entry_points.txt
fastquotes-0.2.0.dist-info/top_level.txt
fastquotes-0.2.0.dist-info/RECORD
