Metadata-Version: 2.1
Name: fastquotes
Version: 0.2.0
Summary: UNKNOWN
Home-page: https://github.com/YangzhenZhao/fastquotes
Author: nocilantro
Author-email: UNKNOWN
License: UNKNOWN
Platform: UNKNOWN
Requires-Dist: requests
Requires-Dist: aiohttp
Requires-Dist: xlrd (==1.2.0)
Requires-Dist: click
Requires-Dist: demjson
